cryostasis/__init__.py
cryostasis/_builtin_helpers.cp311-win_amd64.pyd
cryostasis/detail.py
cryostasis/version.txt
cryostasis-0.3.0.dist-info/METADATA
cryostasis-0.3.0.dist-info/WHEEL
cryostasis-0.3.0.dist-info/top_level.txt
cryostasis-0.3.0.dist-info/RECORD
