Metadata-Version: 2.2
Name: cryostasis
Version: 0.3.0
Author-email: Ilja Manakov <ilja.manakov@gmx.de>
License: MIT License
Project-URL: Homepage, https://github.com/IljaManakov/cryostasis
Project-URL: Documentation, https://cryostasis.readthedocs.io/en/stable/
Project-URL: Issues, https://github.com/IljaManakov/cryostasis/issues
Keywords: static,dataclasses,frozen,constant,const
Classifier: Development Status :: 4 - Beta
Classifier: Intended Audience :: Developers
Classifier: Programming Language :: Python :: 3.9
Classifier: Programming Language :: Python :: 3.10
Classifier: Programming Language :: Python :: 3.11
Classifier: Programming Language :: Python :: 3.12
Classifier: Operating System :: MacOS
Classifier: Operating System :: Microsoft :: Windows
Classifier: Operating System :: POSIX :: Linux
Classifier: Topic :: Software Development
Requires-Python: >=3.9
Provides-Extra: test
Requires-Dist: pytest; extra == "test"
Requires-Dist: psutil; extra == "test"
Provides-Extra: doc
Requires-Dist: sphinx; extra == "doc"
Requires-Dist: sphinx_rtd_theme; extra == "doc"
Requires-Dist: myst-parser; extra == "doc"
Provides-Extra: dev
Requires-Dist: cryostasis[test]; extra == "dev"
Requires-Dist: cryostasis[doc]; extra == "dev"
Requires-Dist: build; extra == "dev"
Requires-Dist: tox; extra == "dev"
Requires-Dist: pytest-cov; extra == "dev"
Requires-Dist: ruff; extra == "dev"
